{
  "app": {
    "signingConfigs": [
      {
        "name": "default",
        "type": "HarmonyOS",
        "material": {
          "certpath": "/Users/roy/.ohos/config/default_neusiri_ui_2WpdYOd-9X4W9Put-ozGNIFz3ybDRsWpUT9AkSLrzFM=.cer",
          "keyAlias": "debugKey",
          "keyPassword": "0000001A588A1241EF52B9DC561D60C03D3BD70DC74F7591705DA1F52435A9CF5B5FE37834D94DA725EB",
          "profile": "/Users/roy/.ohos/config/default_neusiri_ui_2WpdYOd-9X4W9Put-ozGNIFz3ybDRsWpUT9AkSLrzFM=.p7b",
          "signAlg": "SHA256withECDSA",
          "storeFile": "/Users/roy/.ohos/config/default_neusiri_ui_2WpdYOd-9X4W9Put-ozGNIFz3ybDRsWpUT9AkSLrzFM=.p12",
          "storePassword": "0000001AEEF9287EB08EB2239387D0F1227FD80A0DDEA2FA70DD7A445A468F19D172287B7E4075E65956"
        }
      }
    ],
    "products": [
      {
        "name": "default",
        "signingConfig": "default",
        "targetSdkVersion": "5.1.1(19)",
        "compatibleSdkVersion": "5.0.0(12)",
        "runtimeOS": "HarmonyOS",
        "buildOption": {
          "strictMode": {
            "caseSensitiveCheck": true,
            "useNormalizedOHMUrl": true
          }
        }
      }
    ],
    "buildModeSet": [
      {
        "name": "debug",
      },
      {
        "name": "release"
      }
    ]
  },
  "modules": [
    {
      "name": "entry",
      "srcPath": "./entry",
      "targets": [
        {
          "name": "default",
          "applyToProducts": [
            "default"
          ]
        }
      ]
    },
    {
      "name": "utils",
      "srcPath": "./utils",
    }
  ]
}